CHANGES
MANIFEST.in
README
setup.cfg
setup.py
src/rdfadict/README.txt
src/rdfadict/__init__.py
src/rdfadict/extract.py
src/rdfadict/rdfa.py
src/rdfadict.egg-info/PKG-INFO
src/rdfadict.egg-info/SOURCES.txt
src/rdfadict.egg-info/dependency_links.txt
src/rdfadict.egg-info/entry_points.txt
src/rdfadict.egg-info/requires.txt
src/rdfadict.egg-info/top_level.txt
src/rdfadict.egg-info/zip-safe
src/rdfadict/sink/__init__.py
src/rdfadict/sink/graph.py
src/rdfadict/tests/__init__.py
src/rdfadict/tests/test.py
src/rdfadict/tests/test_taskforce.py