Metadata-Version: 1.0
Name: rdfadict
Version: 0.7.4
Summary: An RDFa parser wth a simple dictionary-like interface.
Home-page: http://wiki.creativecommons.org/RdfaDict
Author: Nathan R. Yergler
Author-email: nathan@creativecommons.org
License: MIT
Platform: UNKNOWN
